leadsdb/__init__.py
leadsdb/_async_client.py
leadsdb/client.py
leadsdb/exceptions.py
leadsdb/filters.py
leadsdb/models.py
leadsdb/py.typed
leadsdb-0.9.0.dist-info/METADATA
leadsdb-0.9.0.dist-info/WHEEL
leadsdb-0.9.0.dist-info/licenses/LICENSE
leadsdb-0.9.0.dist-info/RECORD
