Metadata-Version: 2.4
Name: leadsdb
Version: 0.9.0
Summary: Python SDK for the LeadsDB API
Project-URL: Homepage, https://getleadsdb.com
Project-URL: Documentation, https://getleadsdb.com/docs
Project-URL: Repository, https://github.com/gosom/py-leadsdb
Project-URL: Issues, https://github.com/gosom/py-leadsdb/issues
Author-email: LeadsDB <support@getleadsdb.com>
License-Expression: MIT
License-File: LICENSE
Keywords: api,crm,leads,leadsdb,sdk
Classifier: Development Status :: 4 - Beta
Classifier: Intended Audience :: Developers
Classifier: License :: OSI Approved :: MIT License
Classifier: Operating System :: OS Independent
Classifier: Programming Language :: Python :: 3
Classifier: Programming Language :: Python :: 3.10
Classifier: Programming Language :: Python :: 3.11
Classifier: Programming Language :: Python :: 3.12
Classifier: Programming Language :: Python :: 3.13
Classifier: Typing :: Typed
Requires-Python: >=3.10
Requires-Dist: httpx>=0.25.0
Requires-Dist: pydantic>=2.0.0
Provides-Extra: dev
Requires-Dist: mypy>=1.0.0; extra == 'dev'
Requires-Dist: pytest-asyncio>=0.21.0; extra == 'dev'
Requires-Dist: pytest-httpx>=0.21.0; extra == 'dev'
Requires-Dist: pytest>=7.0.0; extra == 'dev'
Requires-Dist: ruff>=0.1.0; extra == 'dev'
